django_better_migrations/__init__.py
django_better_migrations/apps.py
django_better_migrations/migration_writer_patch.py
django_better_migrations/rules.py
django_better_migrations-1.0.3.dist-info/LICENSE
django_better_migrations-1.0.3.dist-info/METADATA
django_better_migrations-1.0.3.dist-info/WHEEL
django_better_migrations-1.0.3.dist-info/RECORD
