Metadata-Version: 2.1
Name: django-better-migrations
Version: 1.0.3
Summary: Adds SQL Output and a Rules system to Django Migrations
Home-page: http://github.com/botify-labs/django-better-migrations
License: MIT
Author: Jean-Baptiste Barth
Author-email: jeanbaptiste.barth@gmail.com
Requires-Python: >=3.7,<4.0
Classifier: Development Status :: 4 - Beta
Classifier: Framework :: Django
Classifier: Framework :: Django :: 2.2
Classifier: Framework :: Django :: 3.0
Classifier: Framework :: Django :: 3.1
Classifier: Framework :: Django :: 3.2
Classifier: Framework :: Django :: 4.0
Classifier: Framework :: Django :: 4.1
Classifier: License :: OSI Approved :: MIT License
Classifier: Programming Language :: Python :: 3
Classifier: Programming Language :: Python :: 3.7
Classifier: Programming Language :: Python :: 3.8
Classifier: Programming Language :: Python :: 3.9
Classifier: Programming Language :: Python :: 3.10
Classifier: Programming Language :: Python :: 3.11
Classifier: Topic :: Database
Requires-Dist: django
Project-URL: Repository, http://github.com/botify-labs/django-better-migrations
